{
  "registry": {
    "entities": [
      { "id": "system.debug.debugger" },
      {
        "id": "game.entity.plant",
        "components": {
          "system.component.model_manager": {
            "armaturebox": "dev/box/armaturebox.fbx"
          }
        }
      }
    ]
  },
  "renderer": {
    "lights": {
      "__sun": {
        "type": "directionalLight",
        "direction": [ -0.5, 0.0, -0.5 ],
        "ambient": [ 0.3, 0.3, 0.3 ],
        "diffuse": [ 1.0, 1.0, 1.0 ],
        "specular": [ 0.1, 0.1, 0.1 ]
      }
    }
  },
  "infrastructure": {
    "tiles": [
      {
        "dimensions": [ 10, 10 ],
        "tiles": [
          [ "grass", "grass", "grass", "grass", "grass", "grass", "grass", "grass", "hardwood2", "hardwood2" ],
          [ "grass", "grass", "grass", "grass", "grass", "grass", "grass", "grass", "hardwood2", "hardwood2" ],
          [ "grass", "grass", "grass", "grass", "grass", "grass", "grass", "grass", "grass", "grass" ],
          [ "grass", "grass", "grass", "grass", "grass", "grass", "grass", "grass", "grass", "grass" ],
          [ "grass", "grass", "grass", "grass", "grass", "grass", "grass", "grass", "grass", "grass" ],
          [ "grass", "grass", "grass", "grass", "grass", "grass", "grass", "grass", "grass", "grass" ],
          [ "grass", "grass", "grass", "grass", "grass", "grass", "grass", "grass", "grass", "grass" ],
          [ "grass", "grass", "grass", "grass", "grass", "grass", "grass", "grass", "grass", "grass" ],
          [ "grass", "grass", "grass", "grass", "grass", "grass", "grass", "grass", "grass", "grass" ],
          [ "grass", "grass", "grass", "grass", "grass", "grass", "grass", "grass", "grass", "grass" ]
        ],
        "vertices": [
          [ 0.0, 0.0, 0.0, 0.0, 0.0, 0.0, 0.0, 0.0, 0.5, 0.5, 0.5 ],
          [ 0.0, 0.0, 0.0, 0.0, 0.0, 0.0, 0.0, 0.0, 0.5, 0.5, 0.5 ],
          [ 0.0, 0.0, 0.0, 0.0, 0.0, 0.0, 0.0, 0.0, 0.5, 0.5, 0.5 ],
          [ 0.0, 0.0, 0.0, 0.0, 0.0, 0.0, 0.0, 0.0, 0.0, 0.0, 0.0 ],
          [ 0.0, 0.0, 0.0, 0.0, 0.0, 0.0, 0.0, 0.0, 0.0, 0.0, 0.0 ],
          [ -0.5, -0.5, -0.5, -0.5, 0.0, 0.0, 0.0, 0.0, 0.0, 0.0, 0.0 ],
          [ -0.5, -0.5, -0.5, -0.5, 0.0, 0.0, 0.0, 0.0, 0.0, 0.0, 0.0 ],
          [ -0.5, -0.5, -0.5, -0.5, 0.0, 0.0, 0.0, 0.0, 0.0, 0.0, 0.0 ],
          [ 0.0, 0.0, 0.0, 0.0, 0.0, 0.0, 0.0, 0.0, 0.0, 0.0, 0.0 ],
          [ 0.0, 0.0, 0.0, 0.0, 0.0, 0.0, 0.0, 0.0, 0.0, 0.0, 0.0 ],
          [ 0.0, 0.0, 0.0, 0.0, 0.0, 0.0, 0.0, 0.0, 0.0, 0.0, 0.0 ]
        ]
      }
    ]
  }
}
